rsa/__init__.py
rsa/key.py
rsa/utility.py
pysafecrypto-0.1.1.dist-info/LICENSE
pysafecrypto-0.1.1.dist-info/METADATA
pysafecrypto-0.1.1.dist-info/WHEEL
pysafecrypto-0.1.1.dist-info/top_level.txt
pysafecrypto-0.1.1.dist-info/RECORD
