Metadata-Version: 2.1
Name: pysafecrypto
Version: 0.1.1
Summary: Python package for handling RSA encrption
Home-page: https://github.com/ScreedVA/pysafecrypto?tab=readme-ov-file
Author: techscreed
Author-email: techscreed@gmail.com
License: MIT
Requires-Python: >=3.6
License-File: LICENSE
